{"resource": "shotchartdetail", "parameters": {"LeagueID": "00", "Season": null, "SeasonType": "Regular Season", "TeamID": 0, "PlayerID": 0, "GameID": "0020300700", "Outcome": null, "Location": null, "Month": 0, "SeasonSegment": null, "DateFrom": null, "DateTo": null, "OpponentTeamID": 0, "VsConference": null, "VsDivision": null, "Position": null, "RookieYear": null, "GameSegment": null, "Period": 0, "LastNGames": 0, "ISTRound": null, "ClutchTime": null, "AheadBehind": null, "PointDiff": null, "RangeType": null, "StartPeriod": null, "EndPeriod": null, "StartRange": null, "EndRange": null, "ContextFilter": null, "ContextMeasure": "FGA"}, "resultSets": [{"name": "Shot_Chart_Detail", "headers": ["GRID_TYPE", "GAME_ID", "GAME_EVENT_ID", "PLAYER_ID", "PLAYER_NAME", "TEAM_ID", "TEAM_NAME", "PERIOD", "MINUTES_REMAINING", "SECONDS_REMAINING", "EVENT_TYPE", "ACTION_TYPE", "SHOT_TYPE", "SHOT_ZONE_BASIC", "SHOT_ZONE_AREA", "SHOT_ZONE_RANGE", "SHOT_DISTANCE", "LOC_X", "LOC_Y", "SHOT_ATTEMPTED_FLAG", "SHOT_MADE_FLAG", "GAME_DATE", "HTM", "VTM"], "rowSet": [["Shot Chart Detail", "0020300700", 3, 1541, "Alvin Williams", 1610612761, "Toronto Raptors", 1, 11, 37, "Made Shot", "Jump Shot", "2PT Field Goal", "Mid-Range", "Left Side Center(LC)", "16-24 ft.", 23, -168, 160, 1, 1, "20040204", "TOR", "ORL"], ["Shot Chart Detail", "0020300700", 4, 436, "Juwan Howard", 1610612753, "Orlando Magic", 1, 11, 22, "Made Shot", "Jump Shot", "2PT Field Goal", "Mid-Range", "Left Side(L)", "16-24 ft.", 18, -181, 2, 1, 1, "20040204", "TOR", "ORL"], ["Shot Chart Detail", "0020300700", 5, 923, "Donyell Marshall", 1610612761, "Toronto Raptors", 1, 11, 7, "Missed Shot", "Jump Shot", "2PT Field Goal", "Mid-Range", "Left Side(L)", "16-24 ft.", 18, -181, 20, 1, 0, "20040204", "TOR", "ORL"], ["Shot Chart Detail", "0020300700", 7, 1713, "Vince Carter", 1610612761, "Toronto Raptors", 1, 11, 2, "Made Shot", "Jump Shot", "3PT Field Goal", "Above the Break 3", "Right Side Center(RC)", "24+ ft.", 25, 189, 164, 1, 1, "20040204", "TOR", "ORL"], ["Shot Chart Detail", "0020300700", 10, 1541, "Alvin Williams", 1610612761, "Toronto Raptors", 1, 10, 39, "Missed Shot", "Running Jump Shot", "2PT Field Goal", "In The Paint (Non-RA)", "Center(C)", "Less Than 8 ft.", 6, 59, 23, 1, 0, "20040204", "TOR", "ORL"], ["Shot Chart Detail", "0020300700", 12, 2586, "Keith Bogans", 1610612753, "Orlando Magic", 1, 10, 32, "Made Shot", "Jump Shot", "3PT Field Goal", "Left Corner 3", "Left Side(L)", "24+ ft.", 23, -232, -3, 1, 1, "20040204", "TOR", "ORL"], ["Shot Chart Detail", "0020300700", 13, 1713, "Vince Carter", 1610612761, "Toronto Raptors", 1, 10, 14, "Missed Shot", "Fadeaway Jump Shot", "2PT Field Goal", "Mid-Range", "Left Side(L)", "8-16 ft.", 15, -140, 77, 1, 0, "20040204", "TOR", "ORL"], ["Shot Chart Detail", "0020300700", 15, 436, "Juwan Howard", 1610612753, "Orlando Magic", 1, 10, 4, "Made Shot", "Running Jump Shot", "2PT Field Goal", "In The Paint (Non-RA)", "Center(C)", "Less Than 8 ft.", 7, 69, 28, 1, 1, "20040204", "TOR", "ORL"], ["Shot Chart Detail", "0020300700", 23, 147, "Jalen Rose", 1610612761, "Toronto Raptors", 1, 9, 22, "Made Shot", "Jump Shot", "2PT Field Goal", "Mid-Range", "Right Side(R)", "8-16 ft.", 14, 144, 12, 1, 1, "20040204", "TOR", "ORL"], ["Shot Chart Detail", "0020300700", 24, 436, "Juwan Howard", 1610612753, "Orlando Magic", 1, 9, 11, "Missed Shot", "Jump Shot", "2PT Field Goal", "Mid-Range", "Right Side(R)", "8-16 ft.", 12, 121, 13, 1, 0, "20040204", "TOR", "ORL"], ["Shot Chart Detail", "0020300700", 27, 2586, "Keith Bogans", 1610612753, "Orlando Magic", 1, 8, 48, "Missed Shot", "Driving Layup Shot", "2PT Field Goal", "Restricted Area", "Center(C)", "Less Than 8 ft.", 0, 0, 0, 1, 0, "20040204", "TOR", "ORL"], ["Shot Chart Detail", "0020300700", 29, 147, "Jalen Rose", 1610612761, "Toronto Raptors", 1, 8, 32, "Missed Shot", "Turnaround Jump Shot", "2PT Field Goal", "Mid-Range", "Right Side(R)", "8-16 ft.", 15, 151, 18, 1, 0, "20040204", "TOR", "ORL"], ["Shot Chart Detail", "0020300700", 31, 1921, "Gordan Giricek", 1610612753, "Orlando Magic", 1, 8, 26, "Made Shot", "Driving Layup Shot", "2PT Field Goal", "Restricted Area", "Center(C)", "Less Than 8 ft.", 0, 0, 0, 1, 1, "20040204", "TOR", "ORL"], ["Shot Chart Detail", "0020300700", 36, 2586, "Keith Bogans", 1610612753, "Orlando Magic", 1, 7, 52, "Missed Shot", "Driving Finger Roll Shot", "2PT Field Goal", "Restricted Area", "Center(C)", "Less Than 8 ft.", 0, 0, 0, 1, 0, "20040204", "TOR", "ORL"], ["Shot Chart Detail", "0020300700", 38, 923, "Donyell Marshall", 1610612761, "Toronto Raptors", 1, 7, 39, "Made Shot", "Jump Shot", "3PT Field Goal", "Left Corner 3", "Left Side(L)", "24+ ft.", 22, -228, -3, 1, 1, "20040204", "TOR", "ORL"], ["Shot Chart Detail", "0020300700", 39, 1921, "Gordan Giricek", 1610612753, "Orlando Magic", 1, 7, 25, "Made Shot", "Jump Shot", "2PT Field Goal", "Mid-Range", "Right Side Center(RC)", "16-24 ft.", 17, 138, 114, 1, 1, "20040204", "TOR", "ORL"], ["Shot Chart Detail", "0020300700", 40, 1713, "Vince Carter", 1610612761, "Toronto Raptors", 1, 7, 9, "Missed Shot", "Running Jump Shot", "2PT Field Goal", "Mid-Range", "Left Side(L)", "8-16 ft.", 14, -140, 17, 1, 0, "20040204", "TOR", "ORL"], ["Shot Chart Detail", "0020300700", 42, 436, "Juwan Howard", 1610612753, "Orlando Magic", 1, 7, 2, "Made Shot", "Layup Shot", "2PT Field Goal", "Restricted Area", "Center(C)", "Less Than 8 ft.", 0, 0, 0, 1, 1, "20040204", "TOR", "ORL"], ["Shot Chart Detail", "0020300700", 43, 2425, "Robert Archibald", 1610612761, "Toronto Raptors", 1, 6, 43, "Missed Shot", "Layup Shot", "2PT Field Goal", "Restricted Area", "Center(C)", "Less Than 8 ft.", 0, 0, 0, 1, 0, "20040204", "TOR", "ORL"], ["Shot Chart Detail", "0020300700", 45, 923, "Donyell Marshall", 1610612761, "Toronto Raptors", 1, 6, 40, "Made Shot", "Layup Shot", "2PT Field Goal", "Restricted Area", "Center(C)", "Less Than 8 ft.", 0, 0, 0, 1, 1, "20040204", "TOR", "ORL"], ["Shot Chart Detail", "0020300700", 49, 436, "Juwan Howard", 1610612753, "Orlando Magic", 1, 6, 24, "Missed Shot", "Jump Shot", "2PT Field Goal", "Mid-Range", "Left Side(L)", "8-16 ft.", 14, -84, 122, 1, 0, "20040204", "TOR", "ORL"], ["Shot Chart Detail", "0020300700", 51, 923, "Donyell Marshall", 1610612761, "Toronto Raptors", 1, 6, 12, "Missed Shot", "Jump Shot", "2PT Field Goal", "Mid-Range", "Right Side(R)", "16-24 ft.", 19, 197, 30, 1, 0, "20040204", "TOR", "ORL"], ["Shot Chart Detail", "0020300700", 53, 923, "Donyell Marshall", 1610612761, "Toronto Raptors", 1, 6, 0, "Made Shot", "Reverse Layup Shot", "2PT Field Goal", "Restricted Area", "Center(C)", "Less Than 8 ft.", 0, 0, 0, 1, 1, "20040204", "TOR", "ORL"], ["Shot Chart Detail", "0020300700", 54, 436, "Juwan Howard", 1610612753, "Orlando Magic", 1, 5, 54, "Made Shot", "Layup Shot", "2PT Field Goal", "Restricted Area", "Center(C)", "Less Than 8 ft.", 0, 0, 0, 1, 1, "20040204", "TOR", "ORL"], ["Shot Chart Detail", "0020300700", 58, 923, "Donyell Marshall", 1610612761, "Toronto Raptors", 1, 5, 34, "Missed Shot", "Running Hook Shot", "2PT Field Goal", "Mid-Range", "Left Side(L)", "8-16 ft.", 10, -97, 43, 1, 0, "20040204", "TOR", "ORL"], ["Shot Chart Detail", "0020300700", 60, 2400, "Drew Gooden", 1610612753, "Orlando Magic", 1, 5, 17, "Missed Shot", "Jump Shot", "2PT Field Goal", "Mid-Range", "Left Side(L)", "8-16 ft.", 10, -102, 22, 1, 0, "20040204", "TOR", "ORL"], ["Shot Chart Detail", "0020300700", 64, 2040, "Jerome Moiso", 1610612761, "Toronto Raptors", 1, 4, 58, "Made Shot", "Slam Dunk Shot", "2PT Field Goal", "Restricted Area", "Center(C)", "Less Than 8 ft.", 0, 0, 0, 1, 1, "20040204", "TOR", "ORL"], ["Shot Chart Detail", "0020300700", 65, 1921, "Gordan Giricek", 1610612753, "Orlando Magic", 1, 4, 31, "Missed Shot", "Jump Shot", "2PT Field Goal", "Mid-Range", "Right Side Center(RC)", "16-24 ft.", 16, 71, 151, 1, 0, "20040204", "TOR", "ORL"], ["Shot Chart Detail", "0020300700", 67, 1713, "Vince Carter", 1610612761, "Toronto Raptors", 1, 4, 22, "Made Shot", "Jump Shot", "2PT Field Goal", "Mid-Range", "Left Side Center(LC)", "16-24 ft.", 21, -174, 132, 1, 1, "20040204", "TOR", "ORL"], ["Shot Chart Detail", "0020300700", 69, 1921, "Gordan Giricek", 1610612753, "Orlando Magic", 1, 4, 7, "Made Shot", "Jump Shot", "2PT Field Goal", "Mid-Range", "Right Side Center(RC)", "16-24 ft.", 16, 90, 143, 1, 1, "20040204", "TOR", "ORL"], ["Shot Chart Detail", "0020300700", 70, 923, "Donyell Marshall", 1610612761, "Toronto Raptors", 1, 3, 47, "Made Shot", "Layup Shot", "2PT Field Goal", "Restricted Area", "Center(C)", "Less Than 8 ft.", 0, 0, 0, 1, 1, "20040204", "TOR", "ORL"], ["Shot Chart Detail", "0020300700", 71, 2586, "Keith Bogans", 1610612753, "Orlando Magic", 1, 3, 28, "Missed Shot", "Jump Shot", "3PT Field Goal", "Above the Break 3", "Right Side Center(RC)", "24+ ft.", 24, 166, 176, 1, 0, "20040204", "TOR", "ORL"], ["Shot Chart Detail", "0020300700", 73, 393, "Rod Strickland", 1610612753, "Orlando Magic", 1, 3, 24, "Made Shot", "Finger Roll Shot", "2PT Field Goal", "Restricted Area", "Center(C)", "Less Than 8 ft.", 0, 0, 0, 1, 1, "20040204", "TOR", "ORL"], ["Shot Chart Detail", "0020300700", 74, 1541, "Alvin Williams", 1610612761, "Toronto Raptors", 1, 3, 11, "Missed Shot", "Driving Finger Roll Shot", "2PT Field Goal", "Restricted Area", "Center(C)", "Less Than 8 ft.", 0, 0, 0, 1, 0, "20040204", "TOR", "ORL"], ["Shot Chart Detail", "0020300700", 76, 1541, "Alvin Williams", 1610612761, "Toronto Raptors", 1, 3, 7, "Made Shot", "Layup Shot", "2PT Field Goal", "Restricted Area", "Center(C)", "Less Than 8 ft.", 0, 0, 0, 1, 1, "20040204", "TOR", "ORL"], ["Shot Chart Detail", "0020300700", 78, 1713, "Vince Carter", 1610612761, "Toronto Raptors", 1, 2, 50, "Missed Shot", "Jump Shot", "2PT Field Goal", "Mid-Range", "Left Side(L)", "8-16 ft.", 15, -156, -1, 1, 0, "20040204", "TOR", "ORL"], ["Shot Chart Detail", "0020300700", 86, 1921, "Gordan Giricek", 1610612753, "Orlando Magic", 1, 2, 32, "Missed Shot", "Jump Shot", "2PT Field Goal", "Mid-Range", "Right Side(R)", "16-24 ft.", 20, 195, 63, 1, 0, "20040204", "TOR", "ORL"], ["Shot Chart Detail", "0020300700", 101, 1713, "Vince Carter", 1610612761, "Toronto Raptors", 1, 1, 38, "Missed Shot", "Jump Shot", "2PT Field Goal", "Mid-Range", "Left Side(L)", "16-24 ft.", 21, -191, 91, 1, 0, "20040204", "TOR", "ORL"], ["Shot Chart Detail", "0020300700", 103, 2400, "Drew Gooden", 1610612753, "Orlando Magic", 1, 1, 20, "Made Shot", "Running Hook Shot", "2PT Field Goal", "In The Paint (Non-RA)", "Center(C)", "8-16 ft.", 8, -5, 81, 1, 1, "20040204", "TOR", "ORL"], ["Shot Chart Detail", "0020300700", 104, 2040, "Jerome Moiso", 1610612761, "Toronto Raptors", 1, 0, 59, "Made Shot", "Turnaround Jump Shot", "2PT Field Goal", "In The Paint (Non-RA)", "Center(C)", "Less Than 8 ft.", 5, 51, 30, 1, 1, "20040204", "TOR", "ORL"], ["Shot Chart Detail", "0020300700", 106, 1960, "Milt Palacio", 1610612761, "Toronto Raptors", 1, 0, 45, "Missed Shot", "Driving Layup Shot", "2PT Field Goal", "Restricted Area", "Center(C)", "Less Than 8 ft.", 0, 0, 0, 1, 0, "20040204", "TOR", "ORL"], ["Shot Chart Detail", "0020300700", 108, 1921, "Gordan Giricek", 1610612753, "Orlando Magic", 1, 0, 40, "Made Shot", "Dunk Shot", "2PT Field Goal", "Restricted Area", "Center(C)", "Less Than 8 ft.", 0, 0, 0, 1, 1, "20040204", "TOR", "ORL"], ["Shot Chart Detail", "0020300700", 109, 1713, "Vince Carter", 1610612761, "Toronto Raptors", 1, 0, 27, "Missed Shot", "Jump Shot", "2PT Field Goal", "Mid-Range", "Center(C)", "16-24 ft.", 19, 46, 192, 1, 0, "20040204", "TOR", "ORL"], ["Shot Chart Detail", "0020300700", 111, 2400, "Drew Gooden", 1610612753, "Orlando Magic", 1, 0, 1, "Missed Shot", "Running Jump Shot", "2PT Field Goal", "Mid-Range", "Left Side(L)", "8-16 ft.", 12, -85, 94, 1, 0, "20040204", "TOR", "ORL"], ["Shot Chart Detail", "0020300700", 113, 1731, "Tyronn Lue", 1610612753, "Orlando Magic", 1, 0, 0, "Made Shot", "Jump Bank Shot", "2PT Field Goal", "Mid-Range", "Left Side(L)", "8-16 ft.", 14, -146, 18, 1, 1, "20040204", "TOR", "ORL"], ["Shot Chart Detail", "0020300700", 119, 147, "Jalen Rose", 1610612761, "Toronto Raptors", 2, 11, 31, "Missed Shot", "Jump Shot", "2PT Field Goal", "In The Paint (Non-RA)", "Center(C)", "Less Than 8 ft.", 7, 0, 76, 1, 0, "20040204", "TOR", "ORL"], ["Shot Chart Detail", "0020300700", 121, 2040, "Jerome Moiso", 1610612761, "Toronto Raptors", 2, 11, 27, "Made Shot", "Jump Bank Shot", "2PT Field Goal", "Mid-Range", "Left Side(L)", "8-16 ft.", 9, -95, 26, 1, 1, "20040204", "TOR", "ORL"], ["Shot Chart Detail", "0020300700", 122, 692, "Andrew DeClercq", 1610612753, "Orlando Magic", 2, 11, 14, "Made Shot", "Hook Shot", "2PT Field Goal", "Mid-Range", "Right Side(R)", "8-16 ft.", 8, 84, 18, 1, 1, "20040204", "TOR", "ORL"], ["Shot Chart Detail", "0020300700", 123, 2050, "Morris Peterson", 1610612761, "Toronto Raptors", 2, 10, 51, "Made Shot", "Jump Shot", "3PT Field Goal", "Left Corner 3", "Left Side(L)", "24+ ft.", 23, -233, -3, 1, 1, "20040204", "TOR", "ORL"], ["Shot Chart Detail", "0020300700", 124, 1731, "Tyronn Lue", 1610612753, "Orlando Magic", 2, 10, 30, "Missed Shot", "Jump Shot", "2PT Field Goal", "Mid-Range", "Right Side Center(RC)", "16-24 ft.", 18, 148, 117, 1, 0, "20040204", "TOR", "ORL"], ["Shot Chart Detail", "0020300700", 126, 2050, "Morris Peterson", 1610612761, "Toronto Raptors", 2, 10, 22, "Made Shot", "Jump Shot", "3PT Field Goal", "Left Corner 3", "Left Side(L)", "24+ ft.", 22, -223, 25, 1, 1, "20040204", "TOR", "ORL"], ["Shot Chart Detail", "0020300700", 127, 2400, "Drew Gooden", 1610612753, "Orlando Magic", 2, 10, 3, "Missed Shot", "Jump Shot", "2PT Field Goal", "Mid-Range", "Left Side(L)", "8-16 ft.", 13, -138, 15, 1, 0, "20040204", "TOR", "ORL"], ["Shot Chart Detail", "0020300700", 129, 147, "Jalen Rose", 1610612761, "Toronto Raptors", 2, 9, 53, "Missed Shot", "Turnaround Jump Shot", "2PT Field Goal", "Mid-Range", "Right Side(R)", "8-16 ft.", 13, 131, 18, 1, 0, "20040204", "TOR", "ORL"], ["Shot Chart Detail", "0020300700", 139, 1960, "Milt Palacio", 1610612761, "Toronto Raptors", 2, 9, 13, "Missed Shot", "Driving Layup Shot", "2PT Field Goal", "Restricted Area", "Center(C)", "Less Than 8 ft.", 0, 0, 0, 1, 0, "20040204", "TOR", "ORL"], ["Shot Chart Detail", "0020300700", 146, 436, "Juwan Howard", 1610612753, "Orlando Magic", 2, 8, 55, "Missed Shot", "Jump Shot", "2PT Field Goal", "Mid-Range", "Left Side(L)", "16-24 ft.", 17, -169, 22, 1, 0, "20040204", "TOR", "ORL"], ["Shot Chart Detail", "0020300700", 148, 147, "Jalen Rose", 1610612761, "Toronto Raptors", 2, 8, 35, "Made Shot", "Jump Shot", "3PT Field Goal", "Above the Break 3", "Left Side Center(LC)", "24+ ft.", 24, -133, 207, 1, 1, "20040204", "TOR", "ORL"], ["Shot Chart Detail", "0020300700", 153, 1731, "Tyronn Lue", 1610612753, "Orlando Magic", 2, 8, 14, "Missed Shot", "Jump Shot", "3PT Field Goal", "Above the Break 3", "Left Side Center(LC)", "24+ ft.", 25, -227, 115, 1, 0, "20040204", "TOR", "ORL"], ["Shot Chart Detail", "0020300700", 155, 923, "Donyell Marshall", 1610612761, "Toronto Raptors", 2, 7, 51, "Missed Shot", "Jump Shot", "2PT Field Goal", "Mid-Range", "Left Side(L)", "16-24 ft.", 20, -168, 114, 1, 0, "20040204", "TOR", "ORL"], ["Shot Chart Detail", "0020300700", 157, 1731, "Tyronn Lue", 1610612753, "Orlando Magic", 2, 7, 26, "Missed Shot", "Fadeaway Jump Shot", "2PT Field Goal", "Mid-Range", "Right Side(R)", "8-16 ft.", 14, 117, 79, 1, 0, "20040204", "TOR", "ORL"], ["Shot Chart Detail", "0020300700", 159, 1921, "Gordan Giricek", 1610612753, "Orlando Magic", 2, 7, 12, "Missed Shot", "Running Jump Shot", "2PT Field Goal", "In The Paint (Non-RA)", "Right Side(R)", "8-16 ft.", 11, 77, 82, 1, 0, "20040204", "TOR", "ORL"], ["Shot Chart Detail", "0020300700", 168, 923, "Donyell Marshall", 1610612761, "Toronto Raptors", 2, 6, 56, "Made Shot", "Layup Shot", "2PT Field Goal", "Restricted Area", "Center(C)", "Less Than 8 ft.", 0, 0, 0, 1, 1, "20040204", "TOR", "ORL"], ["Shot Chart Detail", "0020300700", 169, 436, "Juwan Howard", 1610612753, "Orlando Magic", 2, 6, 39, "Missed Shot", "Hook Shot", "2PT Field Goal", "In The Paint (Non-RA)", "Center(C)", "Less Than 8 ft.", 5, 6, 51, 1, 0, "20040204", "TOR", "ORL"], ["Shot Chart Detail", "0020300700", 172, 393, "Rod Strickland", 1610612753, "Orlando Magic", 2, 6, 16, "Made Shot", "Jump Shot", "2PT Field Goal", "Mid-Range", "Center(C)", "8-16 ft.", 14, -2, 145, 1, 1, "20040204", "TOR", "ORL"], ["Shot Chart Detail", "0020300700", 173, 147, "Jalen Rose", 1610612761, "Toronto Raptors", 2, 5, 57, "Made Shot", "Jump Shot", "3PT Field Goal", "Left Corner 3", "Left Side(L)", "24+ ft.", 22, -223, 0, 1, 1, "20040204", "TOR", "ORL"], ["Shot Chart Detail", "0020300700", 174, 436, "Juwan Howard", 1610612753, "Orlando Magic", 2, 5, 43, "Made Shot", "Turnaround Hook Shot", "2PT Field Goal", "In The Paint (Non-RA)", "Center(C)", "Less Than 8 ft.", 7, -43, 59, 1, 1, "20040204", "TOR", "ORL"], ["Shot Chart Detail", "0020300700", 175, 1960, "Milt Palacio", 1610612761, "Toronto Raptors", 2, 5, 19, "Missed Shot", "Driving Layup Shot", "2PT Field Goal", "Restricted Area", "Center(C)", "Less Than 8 ft.", 0, 0, 0, 1, 0, "20040204", "TOR", "ORL"], ["Shot Chart Detail", "0020300700", 177, 1742, "Shammond Williams", 1610612753, "Orlando Magic", 2, 5, 13, "Missed Shot", "Reverse Layup Shot", "2PT Field Goal", "Restricted Area", "Center(C)", "Less Than 8 ft.", 0, 0, 0, 1, 0, "20040204", "TOR", "ORL"], ["Shot Chart Detail", "0020300700", 179, 2050, "Morris Peterson", 1610612761, "Toronto Raptors", 2, 5, 6, "Made Shot", "Jump Shot", "3PT Field Goal", "Above the Break 3", "Left Side Center(LC)", "24+ ft.", 25, -209, 141, 1, 1, "20040204", "TOR", "ORL"], ["Shot Chart Detail", "0020300700", 180, 1742, "Shammond Williams", 1610612753, "Orlando Magic", 2, 4, 50, "Missed Shot", "Running Jump Shot", "2PT Field Goal", "In The Paint (Non-RA)", "Center(C)", "Less Than 8 ft.", 7, 11, 71, 1, 0, "20040204", "TOR", "ORL"], ["Shot Chart Detail", "0020300700", 182, 1742, "Shammond Williams", 1610612753, "Orlando Magic", 2, 4, 46, "Made Shot", "Jump Shot", "2PT Field Goal", "In The Paint (Non-RA)", "Center(C)", "Less Than 8 ft.", 7, -2, 72, 1, 1, "20040204", "TOR", "ORL"], ["Shot Chart Detail", "0020300700", 183, 147, "Jalen Rose", 1610612761, "Toronto Raptors", 2, 4, 29, "Made Shot", "Jump Shot", "2PT Field Goal", "Mid-Range", "Left Side(L)", "16-24 ft.", 18, -182, 23, 1, 1, "20040204", "TOR", "ORL"], ["Shot Chart Detail", "0020300700", 191, 436, "Juwan Howard", 1610612753, "Orlando Magic", 2, 4, 4, "Made Shot", "Turnaround Hook Shot", "2PT Field Goal", "In The Paint (Non-RA)", "Center(C)", "Less Than 8 ft.", 5, -25, 48, 1, 1, "20040204", "TOR", "ORL"], ["Shot Chart Detail", "0020300700", 192, 1713, "Vince Carter", 1610612761, "Toronto Raptors", 2, 3, 41, "Made Shot", "Jump Shot", "2PT Field Goal", "Mid-Range", "Right Side Center(RC)", "16-24 ft.", 21, 121, 179, 1, 1, "20040204", "TOR", "ORL"], ["Shot Chart Detail", "0020300700", 194, 2585, "Zaza Pachulia", 1610612753, "Orlando Magic", 2, 3, 20, "Made Shot", "Layup Shot", "2PT Field Goal", "Restricted Area", "Center(C)", "Less Than 8 ft.", 0, 0, 0, 1, 1, "20040204", "TOR", "ORL"], ["Shot Chart Detail", "0020300700", 211, 1921, "Gordan Giricek", 1610612753, "Orlando Magic", 2, 2, 31, "Missed Shot", "Jump Shot", "2PT Field Goal", "Mid-Range", "Right Side(R)", "16-24 ft.", 17, 156, 74, 1, 0, "20040204", "TOR", "ORL"], ["Shot Chart Detail", "0020300700", 213, 436, "Juwan Howard", 1610612753, "Orlando Magic", 2, 2, 27, "Missed Shot", "Turnaround Jump Shot", "2PT Field Goal", "Restricted Area", "Center(C)", "Less Than 8 ft.", 2, 19, 17, 1, 0, "20040204", "TOR", "ORL"], ["Shot Chart Detail", "0020300700", 215, 1921, "Gordan Giricek", 1610612753, "Orlando Magic", 2, 2, 23, "Missed Shot", "Jump Shot", "2PT Field Goal", "Mid-Range", "Right Side(R)", "8-16 ft.", 14, 146, 17, 1, 0, "20040204", "TOR", "ORL"], ["Shot Chart Detail", "0020300700", 217, 147, "Jalen Rose", 1610612761, "Toronto Raptors", 2, 2, 0, "Missed Shot", "Jump Shot", "3PT Field Goal", "Left Corner 3", "Left Side(L)", "24+ ft.", 22, -227, -9, 1, 0, "20040204", "TOR", "ORL"], ["Shot Chart Detail", "0020300700", 224, 436, "Juwan Howard", 1610612753, "Orlando Magic", 2, 1, 46, "Made Shot", "Turnaround Jump Shot", "2PT Field Goal", "In The Paint (Non-RA)", "Center(C)", "8-16 ft.", 9, -46, 81, 1, 1, "20040204", "TOR", "ORL"], ["Shot Chart Detail", "0020300700", 225, 1541, "Alvin Williams", 1610612761, "Toronto Raptors", 2, 1, 28, "Made Shot", "Jump Shot", "2PT Field Goal", "Mid-Range", "Right Side(R)", "8-16 ft.", 15, 154, 38, 1, 1, "20040204", "TOR", "ORL"], ["Shot Chart Detail", "0020300700", 226, 436, "Juwan Howard", 1610612753, "Orlando Magic", 2, 1, 6, "Missed Shot", "Turnaround Hook Shot", "2PT Field Goal", "In The Paint (Non-RA)", "Center(C)", "Less Than 8 ft.", 5, -34, 49, 1, 0, "20040204", "TOR", "ORL"], ["Shot Chart Detail", "0020300700", 228, 923, "Donyell Marshall", 1610612761, "Toronto Raptors", 2, 0, 53, "Made Shot", "Jump Shot", "2PT Field Goal", "Mid-Range", "Right Side(R)", "16-24 ft.", 17, 171, 12, 1, 1, "20040204", "TOR", "ORL"], ["Shot Chart Detail", "0020300700", 230, 923, "Donyell Marshall", 1610612761, "Toronto Raptors", 2, 0, 35, "Made Shot", "Driving Dunk Shot", "2PT Field Goal", "Restricted Area", "Center(C)", "Less Than 8 ft.", 0, 0, 0, 1, 1, "20040204", "TOR", "ORL"], ["Shot Chart Detail", "0020300700", 231, 393, "Rod Strickland", 1610612753, "Orlando Magic", 2, 0, 16, "Missed Shot", "Fadeaway Jump Shot", "2PT Field Goal", "Mid-Range", "Left Side(L)", "8-16 ft.", 14, -141, 10, 1, 0, "20040204", "TOR", "ORL"], ["Shot Chart Detail", "0020300700", 233, 923, "Donyell Marshall", 1610612761, "Toronto Raptors", 2, 0, 3, "Made Shot", "Dunk Shot", "2PT Field Goal", "Restricted Area", "Center(C)", "Less Than 8 ft.", 0, 0, 0, 1, 1, "20040204", "TOR", "ORL"], ["Shot Chart Detail", "0020300700", 234, 1921, "Gordan Giricek", 1610612753, "Orlando Magic", 2, 0, 0, "Missed Shot", "Running Jump Shot", "3PT Field Goal", "Above the Break 3", "Left Side Center(LC)", "24+ ft.", 25, -95, 233, 1, 0, "20040204", "TOR", "ORL"], ["Shot Chart Detail", "0020300700", 239, 436, "Juwan Howard", 1610612753, "Orlando Magic", 3, 11, 42, "Missed Shot", "Turnaround Jump Shot", "2PT Field Goal", "Mid-Range", "Left Side(L)", "8-16 ft.", 10, -100, 17, 1, 0, "20040204", "TOR", "ORL"], ["Shot Chart Detail", "0020300700", 241, 1541, "Alvin Williams", 1610612761, "Toronto Raptors", 3, 11, 25, "Made Shot", "Jump Shot", "3PT Field Goal", "Above the Break 3", "Right Side Center(RC)", "24+ ft.", 25, 217, 125, 1, 1, "20040204", "TOR", "ORL"], ["Shot Chart Detail", "0020300700", 245, 1713, "Vince Carter", 1610612761, "Toronto Raptors", 3, 10, 48, "Missed Shot", "Jump Shot", "2PT Field Goal", "Mid-Range", "Left Side Center(LC)", "16-24 ft.", 19, -102, 164, 1, 0, "20040204", "TOR", "ORL"], ["Shot Chart Detail", "0020300700", 247, 1921, "Gordan Giricek", 1610612753, "Orlando Magic", 3, 10, 42, "Missed Shot", "Jump Shot", "3PT Field Goal", "Above the Break 3", "Right Side Center(RC)", "24+ ft.", 24, 146, 197, 1, 0, "20040204", "TOR", "ORL"], ["Shot Chart Detail", "0020300700", 249, 2586, "Keith Bogans", 1610612753, "Orlando Magic", 3, 10, 38, "Missed Shot", "Layup Shot", "2PT Field Goal", "Restricted Area", "Center(C)", "Less Than 8 ft.", 0, 0, 0, 1, 0, "20040204", "TOR", "ORL"], ["Shot Chart Detail", "0020300700", 254, 436, "Juwan Howard", 1610612753, "Orlando Magic", 3, 10, 12, "Made Shot", "Jump Shot", "2PT Field Goal", "Mid-Range", "Left Side Center(LC)", "16-24 ft.", 18, -87, 160, 1, 1, "20040204", "TOR", "ORL"], ["Shot Chart Detail", "0020300700", 256, 1921, "Gordan Giricek", 1610612753, "Orlando Magic", 3, 9, 44, "Made Shot", "Running Jump Shot", "2PT Field Goal", "Mid-Range", "Left Side(L)", "8-16 ft.", 9, -84, 35, 1, 1, "20040204", "TOR", "ORL"], ["Shot Chart Detail", "0020300700", 261, 692, "Andrew DeClercq", 1610612753, "Orlando Magic", 3, 9, 9, "Missed Shot", "Jump Shot", "2PT Field Goal", "Mid-Range", "Center(C)", "16-24 ft.", 17, 39, 166, 1, 0, "20040204", "TOR", "ORL"], ["Shot Chart Detail", "0020300700", 272, 1713, "Vince Carter", 1610612761, "Toronto Raptors", 3, 8, 15, "Made Shot", "Running Jump Shot", "2PT Field Goal", "Mid-Range", "Center(C)", "16-24 ft.", 16, 0, 166, 1, 1, "20040204", "TOR", "ORL"], ["Shot Chart Detail", "0020300700", 273, 393, "Rod Strickland", 1610612753, "Orlando Magic", 3, 7, 58, "Missed Shot", "Jump Shot", "3PT Field Goal", "Above the Break 3", "Right Side Center(RC)", "24+ ft.", 25, 113, 224, 1, 0, "20040204", "TOR", "ORL"], ["Shot Chart Detail", "0020300700", 276, 2400, "Drew Gooden", 1610612753, "Orlando Magic", 3, 7, 36, "Missed Shot", "Running Jump Shot", "2PT Field Goal", "In The Paint (Non-RA)", "Center(C)", "Less Than 8 ft.", 6, 15, 68, 1, 0, "20040204", "TOR", "ORL"], ["Shot Chart Detail", "0020300700", 278, 2425, "Robert Archibald", 1610612761, "Toronto Raptors", 3, 7, 16, "Made Shot", "Jump Shot", "2PT Field Goal", "Mid-Range", "Center(C)", "16-24 ft.", 17, -3, 176, 1, 1, "20040204", "TOR", "ORL"], ["Shot Chart Detail", "0020300700", 279, 2400, "Drew Gooden", 1610612753, "Orlando Magic", 3, 6, 54, "Missed Shot", "Jump Hook Shot", "2PT Field Goal", "In The Paint (Non-RA)", "Center(C)", "Less Than 8 ft.", 7, 67, 35, 1, 0, "20040204", "TOR", "ORL"], ["Shot Chart Detail", "0020300700", 286, 1713, "Vince Carter", 1610612761, "Toronto Raptors", 3, 6, 23, "Made Shot", "Running Jump Shot", "2PT Field Goal", "In The Paint (Non-RA)", "Left Side(L)", "8-16 ft.", 8, -48, 74, 1, 1, "20040204", "TOR", "ORL"], ["Shot Chart Detail", "0020300700", 287, 2586, "Keith Bogans", 1610612753, "Orlando Magic", 3, 6, 15, "Made Shot", "Running Layup Shot", "2PT Field Goal", "Restricted Area", "Center(C)", "Less Than 8 ft.", 0, 0, 0, 1, 1, "20040204", "TOR", "ORL"], ["Shot Chart Detail", "0020300700", 292, 2425, "Robert Archibald", 1610612761, "Toronto Raptors", 3, 5, 51, "Made Shot", "Driving Layup Shot", "2PT Field Goal", "Restricted Area", "Center(C)", "Less Than 8 ft.", 0, 0, 0, 1, 1, "20040204", "TOR", "ORL"], ["Shot Chart Detail", "0020300700", 293, 1921, "Gordan Giricek", 1610612753, "Orlando Magic", 3, 5, 39, "Missed Shot", "Jump Shot", "2PT Field Goal", "Mid-Range", "Left Side Center(LC)", "16-24 ft.", 21, -84, 197, 1, 0, "20040204", "TOR", "ORL"], ["Shot Chart Detail", "0020300700", 295, 1541, "Alvin Williams", 1610612761, "Toronto Raptors", 3, 5, 24, "Missed Shot", "Jump Shot", "2PT Field Goal", "Mid-Range", "Right Side Center(RC)", "16-24 ft.", 19, 92, 169, 1, 0, "20040204", "TOR", "ORL"], ["Shot Chart Detail", "0020300700", 297, 2040, "Jerome Moiso", 1610612761, "Toronto Raptors", 3, 5, 20, "Missed Shot", "Layup Shot", "2PT Field Goal", "Restricted Area", "Center(C)", "Less Than 8 ft.", 0, 0, 0, 1, 0, "20040204", "TOR", "ORL"], ["Shot Chart Detail", "0020300700", 299, 1713, "Vince Carter", 1610612761, "Toronto Raptors", 3, 5, 15, "Missed Shot", "Tip Shot", "2PT Field Goal", "Restricted Area", "Center(C)", "Less Than 8 ft.", 0, 0, 0, 1, 0, "20040204", "TOR", "ORL"], ["Shot Chart Detail", "0020300700", 301, 436, "Juwan Howard", 1610612753, "Orlando Magic", 3, 5, 12, "Made Shot", "Jump Shot", "2PT Field Goal", "Mid-Range", "Left Side(L)", "8-16 ft.", 12, -118, 33, 1, 1, "20040204", "TOR", "ORL"], ["Shot Chart Detail", "0020300700", 302, 147, "Jalen Rose", 1610612761, "Toronto Raptors", 3, 4, 49, "Missed Shot", "Running Jump Shot", "2PT Field Goal", "In The Paint (Non-RA)", "Center(C)", "Less Than 8 ft.", 6, -23, 56, 1, 0, "20040204", "TOR", "ORL"], ["Shot Chart Detail", "0020300700", 304, 147, "Jalen Rose", 1610612761, "Toronto Raptors", 3, 4, 46, "Made Shot", "Turnaround Jump Shot", "2PT Field Goal", "In The Paint (Non-RA)", "Center(C)", "Less Than 8 ft.", 6, 10, 63, 1, 1, "20040204", "TOR", "ORL"], ["Shot Chart Detail", "0020300700", 305, 436, "Juwan Howard", 1610612753, "Orlando Magic", 3, 4, 31, "Missed Shot", "Finger Roll Shot", "2PT Field Goal", "Restricted Area", "Center(C)", "Less Than 8 ft.", 0, 0, 0, 1, 0, "20040204", "TOR", "ORL"], ["Shot Chart Detail", "0020300700", 307, 147, "Jalen Rose", 1610612761, "Toronto Raptors", 3, 4, 11, "Made Shot", "Jump Shot", "2PT Field Goal", "Mid-Range", "Right Side(R)", "8-16 ft.", 15, 156, 18, 1, 1, "20040204", "TOR", "ORL"], ["Shot Chart Detail", "0020300700", 308, 436, "Juwan Howard", 1610612753, "Orlando Magic", 3, 3, 55, "Missed Shot", "Jump Shot", "2PT Field Goal", "Mid-Range", "Center(C)", "16-24 ft.", 16, 6, 168, 1, 0, "20040204", "TOR", "ORL"], ["Shot Chart Detail", "0020300700", 311, 147, "Jalen Rose", 1610612761, "Toronto Raptors", 3, 3, 39, "Made Shot", "Jump Shot", "2PT Field Goal", "Mid-Range", "Right Side(R)", "16-24 ft.", 17, 172, 13, 1, 1, "20040204", "TOR", "ORL"], ["Shot Chart Detail", "0020300700", 320, 2437, "Lonny Baxter", 1610612761, "Toronto Raptors", 3, 2, 57, "Missed Shot", "Jump Shot", "2PT Field Goal", "Mid-Range", "Left Side(L)", "16-24 ft.", 16, -154, 51, 1, 0, "20040204", "TOR", "ORL"], ["Shot Chart Detail", "0020300700", 322, 436, "Juwan Howard", 1610612753, "Orlando Magic", 3, 2, 45, "Made Shot", "Jump Shot", "2PT Field Goal", "In The Paint (Non-RA)", "Left Side(L)", "8-16 ft.", 14, -74, 127, 1, 1, "20040204", "TOR", "ORL"], ["Shot Chart Detail", "0020300700", 329, 1731, "Tyronn Lue", 1610612753, "Orlando Magic", 3, 2, 12, "Made Shot", "Jump Bank Shot", "2PT Field Goal", "Mid-Range", "Left Side(L)", "8-16 ft.", 11, -105, 33, 1, 1, "20040204", "TOR", "ORL"], ["Shot Chart Detail", "0020300700", 331, 1960, "Milt Palacio", 1610612761, "Toronto Raptors", 3, 1, 48, "Missed Shot", "Fadeaway Jump Shot", "2PT Field Goal", "Mid-Range", "Right Side(R)", "8-16 ft.", 13, 123, 43, 1, 0, "20040204", "TOR", "ORL"], ["Shot Chart Detail", "0020300700", 336, 147, "Jalen Rose", 1610612761, "Toronto Raptors", 3, 1, 38, "Made Shot", "Jump Shot", "3PT Field Goal", "Left Corner 3", "Left Side(L)", "24+ ft.", 22, -222, 5, 1, 1, "20040204", "TOR", "ORL"], ["Shot Chart Detail", "0020300700", 337, 2558, "Reece Gaines", 1610612753, "Orlando Magic", 3, 1, 24, "Missed Shot", "Jump Shot", "2PT Field Goal", "Mid-Range", "Right Side Center(RC)", "16-24 ft.", 22, 86, 204, 1, 0, "20040204", "TOR", "ORL"], ["Shot Chart Detail", "0020300700", 339, 2585, "Zaza Pachulia", 1610612753, "Orlando Magic", 3, 1, 20, "Made Shot", "Layup Shot", "2PT Field Goal", "Restricted Area", "Center(C)", "Less Than 8 ft.", 0, 0, 0, 1, 1, "20040204", "TOR", "ORL"], ["Shot Chart Detail", "0020300700", 344, 923, "Donyell Marshall", 1610612761, "Toronto Raptors", 3, 0, 30, "Made Shot", "Jump Shot", "3PT Field Goal", "Right Corner 3", "Right Side(R)", "24+ ft.", 23, 232, -9, 1, 1, "20040204", "TOR", "ORL"], ["Shot Chart Detail", "0020300700", 345, 2585, "Zaza Pachulia", 1610612753, "Orlando Magic", 3, 0, 9, "Made Shot", "Layup Shot", "2PT Field Goal", "Restricted Area", "Center(C)", "Less Than 8 ft.", 0, 0, 0, 1, 1, "20040204", "TOR", "ORL"], ["Shot Chart Detail", "0020300700", 348, 1960, "Milt Palacio", 1610612761, "Toronto Raptors", 3, 0, 0, "Missed Shot", "Fadeaway Jump Shot", "2PT Field Goal", "Mid-Range", "Left Side(L)", "8-16 ft.", 14, -130, 64, 1, 0, "20040204", "TOR", "ORL"], ["Shot Chart Detail", "0020300700", 354, 147, "Jalen Rose", 1610612761, "Toronto Raptors", 4, 11, 28, "Missed Shot", "Jump Shot", "2PT Field Goal", "Mid-Range", "Left Side(L)", "16-24 ft.", 17, -154, 76, 1, 0, "20040204", "TOR", "ORL"], ["Shot Chart Detail", "0020300700", 357, 923, "Donyell Marshall", 1610612761, "Toronto Raptors", 4, 10, 55, "Made Shot", "Layup Shot", "2PT Field Goal", "Restricted Area", "Center(C)", "Less Than 8 ft.", 0, 0, 0, 1, 1, "20040204", "TOR", "ORL"], ["Shot Chart Detail", "0020300700", 358, 2400, "Drew Gooden", 1610612753, "Orlando Magic", 4, 10, 42, "Made Shot", "Turnaround Jump Shot", "2PT Field Goal", "In The Paint (Non-RA)", "Center(C)", "Less Than 8 ft.", 7, -13, 76, 1, 1, "20040204", "TOR", "ORL"], ["Shot Chart Detail", "0020300700", 359, 147, "Jalen Rose", 1610612761, "Toronto Raptors", 4, 10, 28, "Missed Shot", "Jump Shot", "3PT Field Goal", "Right Corner 3", "Right Side(R)", "24+ ft.", 22, 228, 0, 1, 0, "20040204", "TOR", "ORL"], ["Shot Chart Detail", "0020300700", 362, 923, "Donyell Marshall", 1610612761, "Toronto Raptors", 4, 10, 16, "Made Shot", "Driving Dunk Shot", "2PT Field Goal", "Restricted Area", "Center(C)", "Less Than 8 ft.", 0, 0, 0, 1, 1, "20040204", "TOR", "ORL"], ["Shot Chart Detail", "0020300700", 363, 2400, "Drew Gooden", 1610612753, "Orlando Magic", 4, 9, 56, "Missed Shot", "Jump Shot", "2PT Field Goal", "Mid-Range", "Left Side(L)", "16-24 ft.", 19, -161, 110, 1, 0, "20040204", "TOR", "ORL"], ["Shot Chart Detail", "0020300700", 369, 2050, "Morris Peterson", 1610612761, "Toronto Raptors", 4, 9, 34, "Missed Shot", "Driving Layup Shot", "2PT Field Goal", "Restricted Area", "Center(C)", "Less Than 8 ft.", 0, 0, 0, 1, 0, "20040204", "TOR", "ORL"], ["Shot Chart Detail", "0020300700", 371, 923, "Donyell Marshall", 1610612761, "Toronto Raptors", 4, 9, 19, "Made Shot", "Jump Shot", "3PT Field Goal", "Left Corner 3", "Left Side(L)", "24+ ft.", 22, -223, -3, 1, 1, "20040204", "TOR", "ORL"], ["Shot Chart Detail", "0020300700", 372, 2558, "Reece Gaines", 1610612753, "Orlando Magic", 4, 9, 2, "Made Shot", "Jump Shot", "2PT Field Goal", "Mid-Range", "Left Side(L)", "8-16 ft.", 14, -128, 59, 1, 1, "20040204", "TOR", "ORL"], ["Shot Chart Detail", "0020300700", 373, 1541, "Alvin Williams", 1610612761, "Toronto Raptors", 4, 8, 37, "Made Shot", "Jump Shot", "2PT Field Goal", "Mid-Range", "Left Side Center(LC)", "16-24 ft.", 21, -123, 178, 1, 1, "20040204", "TOR", "ORL"], ["Shot Chart Detail", "0020300700", 374, 2558, "Reece Gaines", 1610612753, "Orlando Magic", 4, 8, 21, "Missed Shot", "Jump Shot", "2PT Field Goal", "Mid-Range", "Right Side Center(RC)", "16-24 ft.", 21, 98, 189, 1, 0, "20040204", "TOR", "ORL"], ["Shot Chart Detail", "0020300700", 383, 923, "Donyell Marshall", 1610612761, "Toronto Raptors", 4, 8, 3, "Missed Shot", "Jump Shot", "2PT Field Goal", "Mid-Range", "Left Side(L)", "16-24 ft.", 20, -202, 22, 1, 0, "20040204", "TOR", "ORL"], ["Shot Chart Detail", "0020300700", 388, 923, "Donyell Marshall", 1610612761, "Toronto Raptors", 4, 7, 27, "Missed Shot", "Turnaround Jump Shot", "2PT Field Goal", "In The Paint (Non-RA)", "Center(C)", "Less Than 8 ft.", 6, 67, 20, 1, 0, "20040204", "TOR", "ORL"], ["Shot Chart Detail", "0020300700", 390, 1921, "Gordan Giricek", 1610612753, "Orlando Magic", 4, 7, 11, "Missed Shot", "Running Jump Shot", "2PT Field Goal", "In The Paint (Non-RA)", "Center(C)", "Less Than 8 ft.", 7, -54, 49, 1, 0, "20040204", "TOR", "ORL"], ["Shot Chart Detail", "0020300700", 395, 2400, "Drew Gooden", 1610612753, "Orlando Magic", 4, 6, 28, "Missed Shot", "Reverse Layup Shot", "2PT Field Goal", "Restricted Area", "Center(C)", "Less Than 8 ft.", 0, 0, 0, 1, 0, "20040204", "TOR", "ORL"], ["Shot Chart Detail", "0020300700", 397, 2040, "Jerome Moiso", 1610612761, "Toronto Raptors", 4, 6, 16, "Made Shot", "Driving Finger Roll Shot", "2PT Field Goal", "Restricted Area", "Center(C)", "Less Than 8 ft.", 0, 0, 0, 1, 1, "20040204", "TOR", "ORL"], ["Shot Chart Detail", "0020300700", 398, 2586, "Keith Bogans", 1610612753, "Orlando Magic", 4, 6, 2, "Missed Shot", "Jump Shot", "2PT Field Goal", "Mid-Range", "Right Side Center(RC)", "16-24 ft.", 16, 105, 130, 1, 0, "20040204", "TOR", "ORL"], ["Shot Chart Detail", "0020300700", 400, 1921, "Gordan Giricek", 1610612753, "Orlando Magic", 4, 5, 56, "Missed Shot", "Jump Shot", "2PT Field Goal", "Mid-Range", "Center(C)", "16-24 ft.", 22, -59, 212, 1, 0, "20040204", "TOR", "ORL"], ["Shot Chart Detail", "0020300700", 402, 2050, "Morris Peterson", 1610612761, "Toronto Raptors", 4, 5, 49, "Missed Shot", "Jump Shot", "3PT Field Goal", "Above the Break 3", "Left Side Center(LC)", "24+ ft.", 25, -194, 161, 1, 0, "20040204", "TOR", "ORL"], ["Shot Chart Detail", "0020300700", 409, 2585, "Zaza Pachulia", 1610612753, "Orlando Magic", 4, 5, 21, "Made Shot", "Driving Layup Shot", "2PT Field Goal", "Restricted Area", "Center(C)", "Less Than 8 ft.", 0, 0, 0, 1, 1, "20040204", "TOR", "ORL"], ["Shot Chart Detail", "0020300700", 410, 441, "Lamond Murray", 1610612761, "Toronto Raptors", 4, 5, 1, "Missed Shot", "Jump Shot", "2PT Field Goal", "Mid-Range", "Left Side Center(LC)", "16-24 ft.", 19, -71, 186, 1, 0, "20040204", "TOR", "ORL"], ["Shot Chart Detail", "0020300700", 412, 2558, "Reece Gaines", 1610612753, "Orlando Magic", 4, 4, 53, "Missed Shot", "Driving Finger Roll Shot", "2PT Field Goal", "Restricted Area", "Center(C)", "Less Than 8 ft.", 0, 0, 0, 1, 0, "20040204", "TOR", "ORL"], ["Shot Chart Detail", "0020300700", 414, 2586, "Keith Bogans", 1610612753, "Orlando Magic", 4, 4, 48, "Made Shot", "Jump Shot", "3PT Field Goal", "Above the Break 3", "Right Side Center(RC)", "24+ ft.", 24, 144, 204, 1, 1, "20040204", "TOR", "ORL"], ["Shot Chart Detail", "0020300700", 415, 2427, "Roger Mason Jr.", 1610612761, "Toronto Raptors", 4, 4, 20, "Made Shot", "Driving Layup Shot", "2PT Field Goal", "Restricted Area", "Center(C)", "Less Than 8 ft.", 0, 0, 0, 1, 1, "20040204", "TOR", "ORL"], ["Shot Chart Detail", "0020300700", 416, 1921, "Gordan Giricek", 1610612753, "Orlando Magic", 4, 4, 9, "Missed Shot", "Jump Shot", "2PT Field Goal", "Mid-Range", "Right Side Center(RC)", "16-24 ft.", 17, 92, 150, 1, 0, "20040204", "TOR", "ORL"], ["Shot Chart Detail", "0020300700", 419, 2050, "Morris Peterson", 1610612761, "Toronto Raptors", 4, 3, 48, "Missed Shot", "Jump Shot", "2PT Field Goal", "Mid-Range", "Left Side(L)", "16-24 ft.", 20, -204, 8, 1, 0, "20040204", "TOR", "ORL"], ["Shot Chart Detail", "0020300700", 421, 441, "Lamond Murray", 1610612761, "Toronto Raptors", 4, 3, 38, "Made Shot", "Jump Shot", "2PT Field Goal", "Mid-Range", "Left Side Center(LC)", "16-24 ft.", 21, -103, 194, 1, 1, "20040204", "TOR", "ORL"], ["Shot Chart Detail", "0020300700", 422, 2585, "Zaza Pachulia", 1610612753, "Orlando Magic", 4, 3, 24, "Missed Shot", "Turnaround Jump Shot", "2PT Field Goal", "In The Paint (Non-RA)", "Center(C)", "8-16 ft.", 13, 49, 125, 1, 0, "20040204", "TOR", "ORL"], ["Shot Chart Detail", "0020300700", 424, 441, "Lamond Murray", 1610612761, "Toronto Raptors", 4, 3, 7, "Made Shot", "Driving Finger Roll Shot", "2PT Field Goal", "Restricted Area", "Center(C)", "Less Than 8 ft.", 0, 0, 0, 1, 1, "20040204", "TOR", "ORL"], ["Shot Chart Detail", "0020300700", 425, 2585, "Zaza Pachulia", 1610612753, "Orlando Magic", 4, 2, 45, "Missed Shot", "Driving Hook Shot", "2PT Field Goal", "Restricted Area", "Center(C)", "Less Than 8 ft.", 3, 10, 34, 1, 0, "20040204", "TOR", "ORL"], ["Shot Chart Detail", "0020300700", 427, 441, "Lamond Murray", 1610612761, "Toronto Raptors", 4, 2, 30, "Missed Shot", "Jump Shot", "2PT Field Goal", "Mid-Range", "Left Side Center(LC)", "16-24 ft.", 22, -126, 186, 1, 0, "20040204", "TOR", "ORL"], ["Shot Chart Detail", "0020300700", 429, 2558, "Reece Gaines", 1610612753, "Orlando Magic", 4, 2, 23, "Missed Shot", "Jump Shot", "2PT Field Goal", "Mid-Range", "Left Side Center(LC)", "16-24 ft.", 19, -148, 124, 1, 0, "20040204", "TOR", "ORL"], ["Shot Chart Detail", "0020300700", 431, 2040, "Jerome Moiso", 1610612761, "Toronto Raptors", 4, 2, 1, "Missed Shot", "Jump Shot", "2PT Field Goal", "Mid-Range", "Right Side(R)", "8-16 ft.", 14, 143, 8, 1, 0, "20040204", "TOR", "ORL"], ["Shot Chart Detail", "0020300700", 439, 1960, "Milt Palacio", 1610612761, "Toronto Raptors", 4, 1, 38, "Made Shot", "Jump Shot", "2PT Field Goal", "Mid-Range", "Right Side(R)", "16-24 ft.", 17, 154, 77, 1, 1, "20040204", "TOR", "ORL"], ["Shot Chart Detail", "0020300700", 444, 2585, "Zaza Pachulia", 1610612753, "Orlando Magic", 4, 0, 59, "Made Shot", "Layup Shot", "2PT Field Goal", "Restricted Area", "Center(C)", "Less Than 8 ft.", 0, 0, 0, 1, 1, "20040204", "TOR", "ORL"], ["Shot Chart Detail", "0020300700", 449, 2400, "Drew Gooden", 1610612753, "Orlando Magic", 4, 0, 38, "Made Shot", "Reverse Layup Shot", "2PT Field Goal", "Restricted Area", "Center(C)", "Less Than 8 ft.", 0, 0, 0, 1, 1, "20040204", "TOR", "ORL"], ["Shot Chart Detail", "0020300700", 451, 2427, "Roger Mason Jr.", 1610612761, "Toronto Raptors", 4, 0, 22, "Missed Shot", "Jump Shot", "2PT Field Goal", "Mid-Range", "Right Side Center(RC)", "16-24 ft.", 21, 135, 161, 1, 0, "20040204", "TOR", "ORL"], ["Shot Chart Detail", "0020300700", 453, 2586, "Keith Bogans", 1610612753, "Orlando Magic", 4, 0, 14, "Missed Shot", "Jump Shot", "3PT Field Goal", "Above the Break 3", "Right Side Center(RC)", "24+ ft.", 24, 131, 204, 1, 0, "20040204", "TOR", "ORL"], ["Shot Chart Detail", "0020300700", 455, 2558, "Reece Gaines", 1610612753, "Orlando Magic", 4, 0, 4, "Missed Shot", "Driving Layup Shot", "2PT Field Goal", "Restricted Area", "Center(C)", "Less Than 8 ft.", 0, 0, 0, 1, 0, "20040204", "TOR", "ORL"], ["Shot Chart Detail", "0020300700", 457, 2585, "Zaza Pachulia", 1610612753, "Orlando Magic", 4, 0, 0, "Made Shot", "Layup Shot", "2PT Field Goal", "Restricted Area", "Center(C)", "Less Than 8 ft.", 0, 0, 0, 1, 1, "20040204", "TOR", "ORL"]]}, {"name": "LeagueAverages", "headers": ["GRID_TYPE", "SHOT_ZONE_BASIC", "SHOT_ZONE_AREA", "SHOT_ZONE_RANGE", "FGA", "FGM", "FG_PCT"], "rowSet": [["League Averages", "Above the Break 3", "Back Court(BC)", "Back Court Shot", 109, 5, 0.046], ["League Averages", "Above the Break 3", "Center(C)", "24+ ft.", 5386, 1801, 0.334], ["League Averages", "Above the Break 3", "Left Side Center(LC)", "24+ ft.", 10095, 3479, 0.345], ["League Averages", "Above the Break 3", "Right Side Center(RC)", "24+ ft.", 9959, 3409, 0.342], ["League Averages", "Backcourt", "Back Court(BC)", "Back Court Shot", 336, 8, 0.024], ["League Averages", "In The Paint (Non-RA)", "Center(C)", "8-16 ft.", 5626, 2199, 0.391], ["League Averages", "In The Paint (Non-RA)", "Center(C)", "Less Than 8 ft.", 17559, 6728, 0.383], ["League Averages", "In The Paint (Non-RA)", "Left Side(L)", "8-16 ft.", 2169, 852, 0.393], ["League Averages", "In The Paint (Non-RA)", "Right Side(R)", "8-16 ft.", 1981, 773, 0.39], ["League Averages", "Left Corner 3", "Left Side(L)", "24+ ft.", 5069, 1919, 0.379], ["League Averages", "Mid-Range", "Center(C)", "8-16 ft.", 1923, 771, 0.401], ["League Averages", "Mid-Range", "Center(C)", "16-24 ft.", 6232, 2360, 0.379], ["League Averages", "Mid-Range", "Left Side Center(LC)", "16-24 ft.", 8831, 3465, 0.392], ["League Averages", "Mid-Range", "Left Side(L)", "16-24 ft.", 10325, 4063, 0.394], ["League Averages", "Mid-Range", "Left Side(L)", "8-16 ft.", 11556, 4314, 0.373], ["League Averages", "Mid-Range", "Right Side Center(RC)", "16-24 ft.", 9436, 3682, 0.39], ["League Averages", "Mid-Range", "Right Side(R)", "8-16 ft.", 10735, 3904, 0.364], ["League Averages", "Mid-Range", "Right Side(R)", "16-24 ft.", 8619, 3290, 0.382], ["League Averages", "Restricted Area", "Center(C)", "Less Than 8 ft.", 59358, 34542, 0.582], ["League Averages", "Right Corner 3", "Right Side(R)", "24+ ft.", 4499, 1691, 0.376]]}]}